lektor_jinja_content.py
lektor_jinja_content-0.4.4.dist-info/LICENSE
lektor_jinja_content-0.4.4.dist-info/METADATA
lektor_jinja_content-0.4.4.dist-info/WHEEL
lektor_jinja_content-0.4.4.dist-info/entry_points.txt
lektor_jinja_content-0.4.4.dist-info/top_level.txt
lektor_jinja_content-0.4.4.dist-info/RECORD
